MANIFEST.in
README.md
__init__.py
setup.py
skcmd.el
skcmd.py
skcmd.egg-info/PKG-INFO
skcmd.egg-info/SOURCES.txt
skcmd.egg-info/dependency_links.txt
skcmd.egg-info/top_level.txt