Metadata-Version: 1.1
Name: skcmd
Version: 0.0.7
Summary: Command line interface to Skype
Home-page: http://www.github.com/lsmithso/skcmd
Author: Les Smithson
Author-email: lsmithso@hare.demon.co.uk
License: UNKNOWN
Platform: UNKNOWN
Classifier: Development Status :: 5 - Production/Stable
Classifier: Environment :: Console
Classifier: Intended Audience :: End Users/Desktop
Classifier: Topic :: Adaptive Technologies
Classifier: Topic :: Communications :: Internet Phone
Classifier: Topic :: Communications :: Telephony
Requires: skype4py
Provides: skcmd
